{
  "lang_name": "Bahasa Indonesia",
  "window_title": "NRClipBuilder",
  "lang_label": "Language / Bahasa",
  "filter_group": "Filter",
  "label_keyword": "Kata kunci",
  "label_fields": "Bidang pencarian",
  "label_exclude": "Kata kunci pengecualian",
  "exclude_placeholder": "Contoh: Muroran,Noboribetsu",
  "label_condition": "Kondisi",
  "or_radio": "OR: berisi salah satu",
  "and_radio": "AND: berisi semuanya",
  "label_option": "Opsi",
  "regex_check": "Ekspresi reguler",
  "line_only_check": "Tampilkan/ekspor garis saja",
  "apply_btn": "Filter dan perbarui peta",
  "label_bbox": "Rentang keluaran",
  "use_bbox_check": "Gunakan rentang keluaran",
  "label_bbox_min": "Minimum bujur/lintang",
  "min_lon_placeholder": "Bujur minimum",
  "min_lat_placeholder": "Lintang minimum",
  "label_bbox_max": "Maksimum bujur/lintang",
  "max_lon_placeholder": "Bujur maksimum",
  "max_lat_placeholder": "Lintang maksimum",
  "clear_bbox_btn": "Hapus rentang",
  "label_scale": "Skala keluaran X / Y",
  "info_group": "Informasi pemuatan",
  "info_label_empty": "Belum dimuat",
  "info_label_format": "File sumber: {src}\nTotal: {total:,}\nTersaring: {filtered:,}\nJumlah bidang: {fields}\n{crs}",
  "log_placeholder": "Log",
  "tab_map": "Peta",
  "tab_table": "Atribut",
  "tab_history": "Riwayat",
  "delete_history_btn": "Hapus riwayat terpilih",
  "menu_file": "File",
  "action_open": "Buka...",
  "action_export_geojson": "Ekspor GeoJSON...",
  "action_export_turnout": "Ekspor JSON untuk Turnout...",
  "action_export_nrclip": "Ekspor nrclip...",
  "action_open_html": "Buka pratinjau di browser...",
  "action_quit": "Keluar",
  "history_headers": [
    "Nama",
    "Bujur minimum",
    "Lintang minimum",
    "Bujur maksimum",
    "Lintang maksimum",
    "Tanggal/waktu keluaran"
  ],
  "msg_select_file": "Silakan buka file. Didukung: N05 ZIP / SHP / GeoJSON",
  "msg_loading": "Memuat: {path}",
  "msg_load_success": "Pemuatan selesai: {count:,} features",
  "msg_fields": "Bidang: {fields}",
  "msg_load_error_title": "Kesalahan pemuatan",
  "msg_filter_error_title": "Kesalahan filter",
  "msg_history_deleted": "Riwayat dihapus: {name}",
  "msg_delete_history_warn": "Pilih riwayat yang akan dihapus.",
  "msg_delete_history_title": "Hapus",
  "msg_bbox_warn": "Rentang keluaran belum ditetapkan atau belum diaktifkan.\nTekan tombol “Pilih rentang” pada peta lalu seret untuk memilih area, atau masukkan nilai angka dan centang “Gunakan rentang keluaran”.",
  "msg_bbox_warn_title": "Peringatan",
  "msg_no_export_data": "Tidak ada data untuk diekspor.",
  "msg_export_title": "Ekspor",
  "msg_no_data_in_bbox": "Tidak ada data dalam rentang keluaran yang dipilih.",
  "msg_no_line_in_bbox": "Tidak ada data garis dalam rentang keluaran yang dipilih.",
  "msg_save_geojson": "Simpan GeoJSON",
  "msg_save_success_geojson": "GeoJSON telah disimpan.\n{path}",
  "msg_save_success_title": "Penyimpanan selesai",
  "msg_save_error_title": "Kesalahan penyimpanan",
  "msg_save_turnout": "Simpan JSON untuk Turnout",
  "msg_save_success_turnout": "JSON untuk Turnout telah disimpan.\n{path}\n{nodes} nodes, {ways} ways",
  "msg_save_nrclip": "Simpan nrclip",
  "msg_save_success_nrclip": "nrclip telah disimpan.\n{path}",
  "msg_no_preview_html": "Belum ada HTML pratinjau.",
  "msg_preview_title": "Pratinjau",
  "msg_filtered_count": "Tersaring: {filtered:,} / {total:,} features",
  "dialog_error": "Kesalahan: ",
  "dialog_save_error": "Kesalahan penyimpanan",
  "dialog_open_file_title": "Buka data",
  "map_select_btn": "Pilih rentang",
  "map_select_btn_active": "Memilih rentang (seret untuk memilih)",
  "map_layer_gsi": "Peta Geospatial Information Authority of Japan",
  "map_layer_osm": "OpenStreetMap",
  "map_layer_history": "Riwayat keluaran sebelumnya",
  "map_no_attr": "(tanpa atribut)",
  "clear_history_btn": "Hapus semua riwayat",
  "msg_clear_history_confirm": "Yakin ingin menghapus semua riwayat?",
  "msg_clear_history_title": "Bersihkan riwayat",
  "msg_history_cleared": "Semua riwayat telah dihapus."
}