{
  "lang_name": "Русский",
  "window_title": "NRClipBuilder",
  "lang_label": "Language / Язык",
  "filter_group": "Фильтр",
  "export_group": "Настройки экспорта",
  "label_keyword": "Ключевое слово",
  "label_fields": "Поля поиска",
  "label_exclude": "Исключаемые ключевые слова",
  "exclude_placeholder": "Напр.: Муроран,Ноборибэцу",
  "label_condition": "Условие",
  "or_radio": "OR: содержит любое",
  "and_radio": "AND: содержит все",
  "label_option": "Параметры",
  "regex_check": "Регулярное выражение",
  "line_only_check": "Показывать/экспортировать только линии",
  "apply_btn": "Отфильтровать и обновить карту",
  "label_bbox": "Область вывода",
  "use_bbox_check": "Использовать область вывода",
  "label_bbox_min": "Мин. долгота/широта",
  "min_lon_placeholder": "Мин. долгота",
  "min_lat_placeholder": "Мин. широта",
  "label_bbox_max": "Макс. долгота/широта",
  "max_lon_placeholder": "Макс. долгота",
  "max_lat_placeholder": "Макс. широта",
  "clear_bbox_btn": "Очистить область",
  "label_scale": "Масштаб вывода X / Y",
  "label_spline_tolerance": "Допуск сплайна (м)",
  "label_junction_spacing": "Интервал соединений (м)",
  "label_max_spacing": "Максимальный интервал (м)",
  "label_straight_tolerance": "Допуск прямой линии (м)",
  "info_group": "Информация о загрузке",
  "info_label_empty": "Не загружено",
  "info_label_format": "Исходный файл: {src}\nВсего: {total:,}\nОтобрано: {filtered:,}\nПолей: {fields}\n{crs}",
  "log_placeholder": "Журнал",
  "tab_map": "Карта",
  "tab_table": "Атрибуты",
  "tab_history": "История",
  "delete_history_btn": "Удалить выбранную историю",
  "menu_file": "Файл",
  "action_open": "Открыть...",
  "action_export_geojson": "Экспортировать GeoJSON...",
  "action_export_turnout": "Экспортировать JSON для Turnout...",
  "action_export_nrclip": "Экспортировать nrclip...",
  "action_open_html": "Открыть предпросмотр в браузере...",
  "action_quit": "Выход",
  "history_headers": [
    "Имя",
    "Мин. долгота",
    "Мин. широта",
    "Макс. долгота",
    "Макс. широта",
    "Дата/время вывода"
  ],
  "msg_select_file": "Откройте файл. Поддерживается: N05 ZIP / SHP / GeoJSON",
  "msg_loading": "Загрузка: {path}",
  "msg_load_success": "Загрузка завершена: {count:,} features",
  "msg_fields": "Поля: {fields}",
  "msg_load_error_title": "Ошибка загрузки",
  "msg_filter_error_title": "Ошибка фильтра",
  "msg_history_deleted": "История удалена: {name}",
  "msg_delete_history_warn": "Выберите историю для удаления.",
  "msg_delete_history_title": "Удаление",
  "msg_bbox_warn": "Область вывода не задана или не включена.\nНажмите кнопку «Выбор области» на карте и выделите область перетаскиванием, либо введите числовые значения и отметьте «Использовать область вывода».",
  "msg_bbox_warn_title": "Предупреждение",
  "msg_no_export_data": "Нет данных для вывода.",
  "msg_export_title": "Вывод",
  "msg_no_data_in_bbox": "В выбранной области вывода нет данных.",
  "msg_no_line_in_bbox": "В выбранной области вывода нет линейных данных.",
  "msg_save_geojson": "Сохранить GeoJSON",
  "msg_save_success_geojson": "GeoJSON сохранён.\n{path}",
  "msg_save_success_title": "Сохранение завершено",
  "msg_save_error_title": "Ошибка сохранения",
  "msg_save_turnout": "Сохранить JSON для Turnout",
  "msg_save_success_turnout": "JSON для Turnout сохранён.\n{path}\n{nodes} nodes, {ways} ways",
  "msg_save_nrclip": "Сохранить nrclip",
  "msg_save_success_nrclip": "nrclip сохранён.\n{path}",
  "msg_no_preview_html": "HTML предпросмотра ещё не создан.",
  "msg_preview_title": "Предпросмотр",
  "msg_filtered_count": "Отобрано: {filtered:,} / {total:,} features",
  "dialog_error": "Ошибка: ",
  "dialog_save_error": "Ошибка сохранения",
  "dialog_open_file_title": "Открыть данные",
  "map_select_btn": "Выбор области",
  "map_select_btn_active": "Выбор области (перетащите для выделения)",
  "map_layer_gsi": "Карта Геопространственного управления Японии",
  "map_layer_osm": "OpenStreetMap",
  "map_layer_history": "История предыдущих выводов",
  "map_no_attr": "(нет атрибутов)",
  "clear_history_btn": "Удалить всю историю",
  "msg_clear_history_confirm": "Действительно удалить всю историю?",
  "msg_clear_history_title": "Очистка истории",
  "msg_history_cleared": "Вся история удалена."
}